omoh/__init__.py
siddharth-0.0.1.dist-info/LICENSE
siddharth-0.0.1.dist-info/METADATA
siddharth-0.0.1.dist-info/WHEEL
siddharth-0.0.1.dist-info/top_level.txt
siddharth-0.0.1.dist-info/RECORD
