Metadata-Version: 2.1
Name: siddharth
Version: 0.0.1
Summary: A package to know about your ancestors
Home-page: https://github.com/pypa/sampleproject
Author: Siddharth Yadav
Author-email: siddharth.gohan@gmail.com
License: UNKNOWN
Platform: UNKNOWN
Classifier: Programming Language :: Python :: 3
Classifier: License :: OSI Approved :: MIT License
Classifier: Operating System :: OS Independent
Requires-Python: >=3.6
